arrowhead_client/__init__.py
arrowhead_client/abc.py
arrowhead_client/constants.py
arrowhead_client/device.py
arrowhead_client/dto.py
arrowhead_client/errors.py
arrowhead_client/logs.py
arrowhead_client/request.py
arrowhead_client/response.py
arrowhead_client/rules.py
arrowhead_client/service.py
arrowhead_client/system.py
arrowhead_client/types.py
arrowhead_client/client/__init__.py
arrowhead_client/client/client_async.py
arrowhead_client/client/client_core.py
arrowhead_client/client/client_sync.py
arrowhead_client/client/core_service_responses.py
arrowhead_client/client/core_services.py
arrowhead_client/client/core_system_defaults.py
arrowhead_client/client/implementations.py
arrowhead_client/client/core_service_forms/__init__.py
arrowhead_client/client/core_service_forms/client.py
arrowhead_client/client/core_service_forms/mgmt.py
arrowhead_client/consumer/__init__.py
arrowhead_client/consumer/base.py
arrowhead_client/consumer/implementations/__init__.py
arrowhead_client/consumer/implementations/aiohttp_consumer.py
arrowhead_client/consumer/implementations/requests_consumer.py
arrowhead_client/provider/__init__.py
arrowhead_client/provider/base.py
arrowhead_client/provider/implementations/__init__.py
arrowhead_client/provider/implementations/fastapi_provider.py
arrowhead_client/provider/implementations/httpprovider.py
arrowhead_client/security/__init__.py
arrowhead_client/security/access_policy.py
arrowhead_client/security/access_token.py
arrowhead_client/security/utils.py
arrowhead_client-0.4.4a0.dist-info/LICENSE
arrowhead_client-0.4.4a0.dist-info/METADATA
arrowhead_client-0.4.4a0.dist-info/WHEEL
arrowhead_client-0.4.4a0.dist-info/top_level.txt
arrowhead_client-0.4.4a0.dist-info/RECORD
