Metadata-Version: 2.1
Name: arrowhead-client
Version: 0.4.4a0
Summary: Arrowhead client library
Home-page: https://github.com/arrowhead-f/client-library-python
Author: Jacob Nilsson
Author-email: jacob.nilsson@ltu.se
License: EPL-2.0
Platform: UNKNOWN
Classifier: Development Status :: 3 - Alpha
Classifier: Intended Audience :: Developers
Classifier: Programming Language :: Python :: 3
Classifier: Programming Language :: Python :: 3.7
Classifier: Programming Language :: Python :: 3.8
Classifier: Programming Language :: Python :: 3.9
Classifier: Operating System :: POSIX :: Linux
Classifier: License :: OSI Approved :: Eclipse Public License 2.0 (EPL-2.0)
Requires-Python: >=3.7
License-File: LICENSE
Requires-Dist: FastAPI
Requires-Dist: aiohttp[standard]
Requires-Dist: uvicorn
Requires-Dist: Flask (>=1.0.2)
Requires-Dist: requests (>=2.21)
Requires-Dist: cryptography (>=3.3.2)
Requires-Dist: jwcrypto (==0.8)
Requires-Dist: six
